timething/__init__.py
timething/align.py
timething/cli.py
timething/cutter.py
timething/dataset.py
timething/job.py
timething/models.yaml
timething/text.py
timething/utils.py
timething/viz.py
timething-0.0.27.dist-info/LICENSE.txt
timething-0.0.27.dist-info/METADATA
timething-0.0.27.dist-info/WHEEL
timething-0.0.27.dist-info/entry_points.txt
timething-0.0.27.dist-info/top_level.txt
timething-0.0.27.dist-info/RECORD
