Metadata-Version: 2.1
Name: timething
Version: 0.0.27
Summary: Aligning text transcripts with their audio recordings.
Home-page: https://github.com/feldberlin/timething
Author: FELD Berlin
Author-email: rany@feldberlin.com
License: MIT
Project-URL: Bug Tracker, https://github.com/feldberlin/timething/issues
Classifier: Programming Language :: Python :: 3
Classifier: Programming Language :: Python :: 3 :: Only
Classifier: Programming Language :: Python :: 3.7
Classifier: Programming Language :: Python :: 3.8
Requires-Python: >=3.7
License-File: LICENSE.txt
Requires-Dist: click
Requires-Dist: datasets
Requires-Dist: num2words
Requires-Dist: numpy
Requires-Dist: torch
Requires-Dist: tokenizers (==0.10.1)
Requires-Dist: torchaudio
Requires-Dist: transformers (==4.4.2)
